---
title: 深入理解 Java Lambda 表达式 
category: Java 
tag: Java
excerpt_separator: <!--more-->
---

## 前言

Lambda 是在 Java 8 之后的新特性，这也是我在工作中经常用到的 API，对于 Lambda 如何运用，这里不再赘述，这里我主要想分享一些 Lambda 的底层原理。

<!--more-->

## 简单的用例
下面是一个简单的 Lambda 表达式用例

```java
package org.hein;

public class Lambda {

    @FunctionalInterface
    public interface LambdaInterface {
        void run();
    }

    public static void foo(LambdaInterface lambda) {
        lambda.run();
    }

    public static void main(String[] args) {
        LambdaInterface lambda = () -> System.out.println("Hello World");
        foo(lambda);
    }
}
```

该例子对应的完整字节码如下：

```java
Classfile /Users/hejin/project/java-code/src/main/java/org/hein/Lambda.class
  Last modified 2024年9月7日; size 1198 bytes
  SHA-256 checksum da4e7dd07b7e739763db5db7eac83163fac862b9234f70e97ff0cf43ae297f41
  Compiled from "Lambda.java"
public class org.hein.Lambda
  minor version: 0
  major version: 61
  flags: (0x0021) ACC_PUBLIC, ACC_SUPER
  this_class: #16                         // org/hein/Lambda
  super_class: #2                         // java/lang/Object
  interfaces: 0, fields: 0, methods: 4, attributes: 4
Constant pool:
   #1 = Methodref          #2.#3          // java/lang/Object."<init>":()V
   #2 = Class              #4             // java/lang/Object
   #3 = NameAndType        #5:#6          // "<init>":()V
   #4 = Utf8               java/lang/Object
   #5 = Utf8               <init>
   #6 = Utf8               ()V
   #7 = InterfaceMethodref #8.#9          // org/hein/Lambda$LambdaInterface.run:()V
   #8 = Class              #10            // org/hein/Lambda$LambdaInterface
   #9 = NameAndType        #11:#6         // run:()V
  #10 = Utf8               org/hein/Lambda$LambdaInterface
  #11 = Utf8               run
  #12 = InvokeDynamic      #0:#13         // #0:run:()Lorg/hein/Lambda$LambdaInterface;
  #13 = NameAndType        #11:#14        // run:()Lorg/hein/Lambda$LambdaInterface;
  #14 = Utf8               ()Lorg/hein/Lambda$LambdaInterface;
  #15 = Methodref          #16.#17        // org/hein/Lambda.foo:(Lorg/hein/Lambda$LambdaInterface;)V
  #16 = Class              #18            // org/hein/Lambda
  #17 = NameAndType        #19:#20        // foo:(Lorg/hein/Lambda$LambdaInterface;)V
  #18 = Utf8               org/hein/Lambda
  #19 = Utf8               foo
  #20 = Utf8               (Lorg/hein/Lambda$LambdaInterface;)V
  #21 = Fieldref           #22.#23        // java/lang/System.out:Ljava/io/PrintStream;
  #22 = Class              #24            // java/lang/System
  #23 = NameAndType        #25:#26        // out:Ljava/io/PrintStream;
  #24 = Utf8               java/lang/System
  #25 = Utf8               out
  #26 = Utf8               Ljava/io/PrintStream;
  #27 = String             #28            // Hello World
  #28 = Utf8               Hello World
  #29 = Methodref          #30.#31        // java/io/PrintStream.println:(Ljava/lang/String;)V
  #30 = Class              #32            // java/io/PrintStream
  #31 = NameAndType        #33:#34        // println:(Ljava/lang/String;)V
  #32 = Utf8               java/io/PrintStream
  #33 = Utf8               println
  #34 = Utf8               (Ljava/lang/String;)V
  #35 = Utf8               Code
  #36 = Utf8               LineNumberTable
  #37 = Utf8               main
  #38 = Utf8               ([Ljava/lang/String;)V
  #39 = Utf8               lambda$main$0
  #40 = Utf8               SourceFile
  #41 = Utf8               Lambda.java
  #42 = Utf8               NestMembers
  #43 = Utf8               BootstrapMethods
  #44 = MethodHandle       6:#45          // REF_invokeStatic java/lang/invoke/LambdaMetafactory.metafactory:(Ljava/lang/invoke/MethodHandles$Lookup;Ljava/lang/String;Ljava/lang/invoke/MethodType;Ljava/lang/invoke/MethodType;Ljava/lang/invoke/MethodHandle;Ljava/lang/invoke/MethodType;)Ljava/lang/invoke/CallSite;
  #45 = Methodref          #46.#47        // java/lang/invoke/LambdaMetafactory.metafactory:(Ljava/lang/invoke/MethodHandles$Lookup;Ljava/lang/String;Ljava/lang/invoke/MethodType;Ljava/lang/invoke/MethodType;Ljava/lang/invoke/MethodHandle;Ljava/lang/invoke/MethodType;)Ljava/lang/invoke/CallSite;
  #46 = Class              #48            // java/lang/invoke/LambdaMetafactory
  #47 = NameAndType        #49:#50        // metafactory:(Ljava/lang/invoke/MethodHandles$Lookup;Ljava/lang/String;Ljava/lang/invoke/MethodType;Ljava/lang/invoke/MethodType;Ljava/lang/invoke/MethodHandle;Ljava/lang/invoke/MethodType;)Ljava/lang/invoke/CallSite;
  #48 = Utf8               java/lang/invoke/LambdaMetafactory
  #49 = Utf8               metafactory
  #50 = Utf8               (Ljava/lang/invoke/MethodHandles$Lookup;Ljava/lang/String;Ljava/lang/invoke/MethodType;Ljava/lang/invoke/MethodType;Ljava/lang/invoke/MethodHandle;Ljava/lang/invoke/MethodType;)Ljava/lang/invoke/CallSite;
  #51 = MethodType         #6             //  ()V
  #52 = MethodHandle       6:#53          // REF_invokeStatic org/hein/Lambda.lambda$main$0:()V
  #53 = Methodref          #16.#54        // org/hein/Lambda.lambda$main$0:()V
  #54 = NameAndType        #39:#6         // lambda$main$0:()V
  #55 = Utf8               InnerClasses
  #56 = Utf8               LambdaInterface
  #57 = Class              #58            // java/lang/invoke/MethodHandles$Lookup
  #58 = Utf8               java/lang/invoke/MethodHandles$Lookup
  #59 = Class              #60            // java/lang/invoke/MethodHandles
  #60 = Utf8               java/lang/invoke/MethodHandles
  #61 = Utf8               Lookup
{
  public org.hein.Lambda();
    descriptor: ()V
    flags: (0x0001) ACC_PUBLIC
    Code:
      stack=1, locals=1, args_size=1
         0: aload_0
         1: invokespecial #1                  // Method java/lang/Object."<init>":()V
         4: return
      LineNumberTable:
        line 3: 0

  public static void foo(org.hein.Lambda$LambdaInterface);
    descriptor: (Lorg/hein/Lambda$LambdaInterface;)V
    flags: (0x0009) ACC_PUBLIC, ACC_STATIC
    Code:
      stack=1, locals=1, args_size=1
         0: aload_0
         1: invokeinterface #7,  1            // InterfaceMethod org/hein/Lambda$LambdaInterface.run:()V
         6: return
      LineNumberTable:
        line 11: 0
        line 12: 6

  public static void main(java.lang.String[]);
    descriptor: ([Ljava/lang/String;)V
    flags: (0x0009) ACC_PUBLIC, ACC_STATIC
    Code:
      stack=1, locals=2, args_size=1
         0: invokedynamic #12,  0             // InvokeDynamic #0:run:()Lorg/hein/Lambda$LambdaInterface;
         5: astore_1
         6: aload_1
         7: invokestatic  #15                 // Method foo:(Lorg/hein/Lambda$LambdaInterface;)V
        10: return
      LineNumberTable:
        line 15: 0
        line 16: 6
        line 17: 10
}
SourceFile: "Lambda.java"
NestMembers:
  org/hein/Lambda$LambdaInterface
BootstrapMethods:
  0: #44 REF_invokeStatic java/lang/invoke/LambdaMetafactory.metafactory:(Ljava/lang/invoke/MethodHandles$Lookup;Ljava/lang/String;Ljava/lang/invoke/MethodType;Ljava/lang/invoke/MethodType;Ljava/lang/invoke/MethodHandle;Ljava/lang/invoke/MethodType;)Ljava/lang/invoke/CallSite;
    Method arguments:
      #51 ()V
      #52 REF_invokeStatic org/hein/Lambda.lambda$main$0:()V
      #51 ()V
InnerClasses:
  public static #56= #8 of #16;           // LambdaInterface=class org/hein/Lambda$LambdaInterface of class org/hein/Lambda
  public static final #61= #57 of #59;    // Lookup=class java/lang/invoke/MethodHandles$Lookup of class java/lang/invoke/MethodHandles
```

## invokedynamic 指令
这里我们先简单了解一下 invokedynamic 指令以及其特点。

invokedynamic 是 JVM 在 Java 7 引入的，它允许在运行时动态解析方法调用的目标。这个特性主要是为了支持动态语言在 JVM 上的高效实现，同时也为静态语言提供了一种更灵活的方式来处理某些类型的动态行为。

invokedynamic 主要有以下特点：

1. 动态解析：invokedynamic 指令允许在运行时（非编译时）才决定要调用的方法。所以可以用于实现动态语言的行为，如方法查找、元编程等。
2. Bootstrap 方法：为了实现动态解析，invokedynamic 需要一个引导方法（bootstrap method），该方法在class 文件中定义，并且由 JVM 在 invokedynamic 指令执行前调用。引导方法可以通过修改方法句柄和方法类型，从而影响实际调用的目标。
3. Lambda 表达式支持：invokedynamic 也是实现 Lambda 表达式的基石。当编译器遇到 Lambda 表达式时，它会生成一个匿名函数接口的实现，并通过 invokedynamic 调用来执行这个匿名函数。
4. 性能优化：由于 invokedynamic 可以与内联缓存和其他 JIT 编译技术相结合，因此它能够提供很好的性能，特别是在动态语言的实现中。
5. 方法句柄 API：Java 7 引入的方法句柄（`java.lang.invoke.MethodHandle`）API 也依赖于 invokedynamic 指令来实现其功能，方法句柄提供了一种更安全和更强大的方式来反射地调用方法。

了解了 invokedynamic 指令之后，我们再来关注 main 方法的字节码指令：

```java
public static void main(java.lang.String[]);
  descriptor: ([Ljava/lang/String;)V
  flags: (0x0009) ACC_PUBLIC, ACC_STATIC
  Code:
    stack=1, locals=2, args_size=1
       0: invokedynamic #12,  0             // InvokeDynamic #0:run:()Lorg/hein/Lambda$LambdaInterface;
       5: astore_1
       6: aload_1
       7: invokestatic  #15                 // Method foo:(Lorg/hein/Lambda$LambdaInterface;)V
      10: return
    LineNumberTable:
      line 15: 0
      line 16: 6
      line 17: 10
```

在标记 0 处的字节码表示正在使用 invokedynamic 来调用某个方法，并将返回值存储到栈中。

## invokedynamic 如何工作
当类加载器加载了一个使用了 invokedynamic 指令的 class 时，要调用的方法是无法提前预知的，这和 JVM 其他方法调用的字节码不一样。

比如 invokestatic 和 invokespecial 指令的调用目标是在编译时就确定了，而对于 invokevirtual 和 invokeinterface 来说，虽然调用目标需要在运行时才能确定，但选择的目标也受限于 Java 语言规范和类型系统的约束，所以，至少有部分调用信息是在编译期能确定的。

在使用了 invokedynamic 的类的常量池中，存在一个特殊的常量，invokedynamic 指令正是通过它来实现动态调用的，这个常量包含了动态方法调用所需的额外信息，又被称为「引导方法（Bootstrap Method，BSM）」。

这是 invokedynamic 实现的关键，每个 invokedynamic 的调用点（call site）都对应了一个 BSM 的常量池项。

比如上面的字节码中，BSM 如下：

```java
BootstrapMethods:
  0: #44 REF_invokeStatic java/lang/invoke/LambdaMetafactory.metafactory:(Ljava/lang/invoke/MethodHandles$Lookup;Ljava/lang/String;Ljava/lang/invoke/MethodType;Ljava/lang/invoke/MethodType;Ljava/lang/invoke/MethodHandle;Ljava/lang/invoke/MethodType;)Ljava/lang/invoke/CallSite;
    Method arguments:
      #51 ()V
      #52 REF_invokeStatic org/hein/Lambda.lambda$main$0:()V
      #51 ()V
```

invokedynamic 指令的调用点在类加载时是「未链接的」，只有调用 BSM 之后才能确定具体要调用的方法，返回的 CallSite 对象会会关联到调用点上。

要看懂 BootstrapMethods 中的方法，又不得不了解一下 Java 7 引入的一套新的 API，方法句柄（Method Handle）。

## 方法句柄
Java 反射诞生时还没有集合和泛型，所以对应的方法签名在反射 API 中只能通过 Class[] 处理，这很笨重并且容易出问题。

所以在 Java 7 中，引入了方法句柄，相较于反射，

1. 方法句柄 API 在编译时就进行了类型检查，因此在运行时更加安全，不容易抛出 ClassCastException。
2. 方法句柄 API 在查询上下文时只会返回查询对象创建时所在的域能访问的方法，这不像反射 API 可以使用`setAccessible()`来绕过检查，也就是说方法句柄 API 始终是安全的。
3. 方法句柄 API 在大多数情况下性能也要比反射 API 更高，还可以利用 JIT 编译器优化。
4. 方法句柄 API 提供了更多动态操作的方法，比如条件调用、方法组合等。
5. 唯一的不足可能在于反射 API 更为简单易用，而方法句柄 API 稍微复杂一些。

这套 API 的核心在 java.lang.invoke 包中，是 invokedynamic 的基础，但也可以单独使用，我们可以将其简单理解为更现代、更安全的反射机制。

为了解决方法签名如何表示的问题，MethodHandles 引入了 MethodType 类，这是一个简单的「不可变」类型，它有许多非常有用的特性，MethodType 可以用来表示方法的类型签名，包括返回值类型以及参数类型，其设计于解决反射中的 Class[] 问题。

下面简单使用一下方法句柄 API。

```java
package org.hein;

import java.lang.invoke.MethodHandle;
import java.lang.invoke.MethodHandles;
import java.lang.invoke.MethodType;

public class MethodHandleTest {

    public static void main(String[] args) throws Throwable {
        // 获取 Lookup 对象
        MethodHandles.Lookup lookup = MethodHandles.lookup();
        // 使用 findXxx 方法查找并获取方法句柄
        // 比如 findStatic、findConstructor、findGetter、findSetter、findSpecial、findVirtual 等
        // methodType(返回值类型, 参数类型 ...)
        MethodType methodType = MethodType.methodType(void.class, String.class);
        MethodHandle foo = lookup.findStatic(MethodHandleTest.class, "foo", methodType);
        // 方法句柄的 invokeXxx 方法用于执行对应的方法
        foo.invokeExact("Hello World");
    }

    public static void foo(String msg) {
        System.out.println(msg);
    }
}
```

## 再谈引导方法
基本认识了方法句柄之后，再来看一看引导方法。

现在 BSM 的概念应该更为明确了，当程序执行到 invokedynamic 的调用点时，会调用相关联的 BSM，BSM 会返回一个调用点对象，它包含了一个方法句柄，会指向最终绑定到这个调用点的方法上。

比如上面的字节码中，BSM 如下：

```java
BootstrapMethods:
  0: #44 REF_invokeStatic java/lang/invoke/LambdaMetafactory.metafactory:(Ljava/lang/invoke/MethodHandles$Lookup;Ljava/lang/String;Ljava/lang/invoke/MethodType;Ljava/lang/invoke/MethodType;Ljava/lang/invoke/MethodHandle;Ljava/lang/invoke/MethodType;)Ljava/lang/invoke/CallSite;
    Method arguments:
      #51 ()V
      #52 REF_invokeStatic org/hein/Lambda.lambda$main$0:()V
      #51 ()V
```

这里实际执行了 java/lang/invoke/LambdaMetafactory.metafactory 方法，如下：

```java
public static CallSite metafactory(MethodHandles.Lookup caller,
                                   String invokedName,
                                   MethodType invokedType,
                                   MethodType samMethodType,
                                   MethodHandle implMethod,
                                   MethodType instantiatedMethodType)
        throws LambdaConversionException {
    AbstractValidatingLambdaMetafactory mf;
    mf = new InnerClassLambdaMetafactory(caller, invokedType,
                                         invokedName, samMethodType,
                                         implMethod, instantiatedMethodType,
                                         false, EMPTY_CLASS_ARRAY, EMPTY_MT_ARRAY);
    mf.validateMetafactoryArgs();
    return mf.buildCallSite();
}
```

metafactory 方法的入参包括查询对象、用来确保静态类型安全的方法类型（method types）、以及指向 lambda 表达式的静态私有方法的方法句柄。

测试用例加上 vm 参数 -Djdk.internal.lambda.dumpProxyClasses 后，就可以看到为 lambda 生成的内部类。

进行反编译：

```java
javap -c -p Lambda\$\$Lambda\$1.class
```

```java
final class org.hein.Lambda$$Lambda$1 implements org.hein.Lambda$LambdaInterface {
  private org.hein.Lambda$$Lambda$1();
    Code:
       0: aload_0
       1: invokespecial #10                 // Method java/lang/Object."<init>":()V
       4: return

  public void run();
    Code:
       0: invokestatic  #17                 // Method org/hein/Lambda.lambda$main$0:()V
       3: return
}
```

而 metafactory 方法，会为每个 lambda 表达式生成这样的内部类，但这些类是动态生成的，也不会回写到磁盘上，这种实现机制在未来的 Java 版本中可能会发生变化，这样原有的 lambda 表达式也都能受益于后续新的实现。

在 Java 8 和 Java 9 中，InnerClassLambdaMetafactory 的实现是使用了一个轻微修改过的 ASM 字节码库，它发布在 jdk.internal.org.objectweb.asm 包下。

它能动态地生成 Lambda 表达式的实现类，同时还保证了未来的可扩展性和对 JIT 的友好性。

它的实现方式也是最简单的，调用点一旦返回后就不会再变化了，返回的调用点类型是 ConstantCallSite。

当然 invokedynamic 还能支持更复杂的场景，比如调用点可以是可变的甚至是实现 volatile 变量类似的语义。当然这些情况也更复杂、更难以处理，但它们为平台的动态扩展提供了最大的可能性。

## 总结
至此，我们可以知道，Lambda 表达式的实现，是由 JVM 的 invokedynamic 指令调用的引导方法 BSM，通过 ASM 技术创建了实现特定接口、并在接口定义的方法实现中包含了 Lambda 表达式的内容的匿名内部类，并返回 ConstantCallSite 调用点对象进行调用。

参考：

- <a href="http://ifeve.com/jvm%e4%b9%8b%e5%8a%a8%e6%80%81%e6%96%b9%e6%b3%95%e8%b0%83%e7%94%a8%ef%bc%9ainvokedynamic/#google_vignette">JVM之动态方法调用：invokedynamic | 并发编程网 – ifeve.com</a>
